permissions.py
file_permissions-0.2.dist-info/METADATA
file_permissions-0.2.dist-info/RECORD
file_permissions-0.2.dist-info/WHEEL
file_permissions-0.2.dist-info/top_level.txt
