Metadata-Version: 2.1
Name: file-permissions
Version: 0.2
Summary: A tiny wrapper to get information about file permissions
Home-page: https://github.com/andreyrusanov/permissions
Author: Andrii Rusanov
Author-email: andrey@rusanov.me
License: MIT
Platform: UNKNOWN
Classifier: License :: OSI Approved :: MIT License
Classifier: Programming Language :: Python
Classifier: Programming Language :: Python :: 3
